{"signo":"Aquario","data":"2026-07-15","idioma":"pt-BR","fato_historico":"1826: Ocorre o congresso pan-americano no Panamá, sob auspícios de Simón Bolívar, que tinha por objetivo unificar os novos Estados americanos.","cache":false,"titulo":"Sintonia com o Coletivo","energia_do_dia":"Assim como o sonho de unir povos sob um mesmo ideal, hoje sua mente pode buscar conexões mais profundas e colaborativas. É um bom momento para considerar como suas ideias podem somar ao todo. Talvez seja o dia ideal para alinhar seus projetos pessoais com propósitos que tragam benefícios genuínos para as pessoas ao seu redor.","palavra_do_dia":"União","frase_do_dia":"Sua voz é uma peça fundamental na melodia do coletivo hoje.","simbolo_emoji":"🌐","simbolo_nome":"Rede","cor_nome":"Azul Profundo","numero_simbolico":26,"significado_numero":"Representa a capacidade de diplomacia e a construção de pontes entre ideais.","conselho":"Escute as sugestões alheias, pois nelas podem residir as chaves da inovação.","numeros_sorte":[10,11,27,31,33,50],"indicadores_dia":{"amor":87,"saudade":16,"trabalho":40,"financas":22,"dinheiro":97,"sorte":37,"humor":100,"energia":91,"saude":54,"amizade":10,"estudos":46,"criatividade":30}}