{"signo":"Leao","data":"2026-07-15","idioma":"en-US","fato_historico":"1916: In Seattle, Washington, William Boeing and George Conrad Westervelt incorporate Pacific Aero Products (later renamed Boeing).","cache":false,"titulo":"Soar High Toward New Horizons","energia_do_dia":"The stars invite you to embrace your inner visionary today. Just as a bold dream once took flight in the Pacific skies to reshape the world, you may find that your own ambitions are ready to lift off. Consider nurturing your creativity and perhaps drafting the blueprints for a grand adventure that captures your golden, radiant spirit.","palavra_do_dia":"Elevation","frase_do_dia":"Your unique vision has the power to carry you toward incredible new heights.","simbolo_emoji":"✈️","simbolo_nome":"Airplane","cor_nome":"Solar Gold","numero_simbolico":7,"significado_numero":"A powerful number representing inner wisdom and spiritual exploration.","conselho":"Trust your bold ideas and prepare to embark on an exciting journey.","numeros_sorte":[8,17,19,44,49,52],"indicadores_dia":{"amor":73,"saudade":65,"trabalho":74,"financas":98,"dinheiro":43,"sorte":36,"humor":28,"energia":91,"saude":47,"amizade":98,"estudos":35,"criatividade":17}}