{"signo":"Peixes","data":"2026-07-15","idioma":"pt-BR","fato_historico":"1888: O estratovulcão Monte Bandai entra em erupção, matando aproximadamente 500 pessoas na província de Fukushima, Japão.","cache":false,"titulo":"Fluindo com a sensibilidade interior","energia_do_dia":"Assim como as forças profundas da terra que, em um passado distante, transformaram a paisagem do Japão, hoje sua sensibilidade pode estar em erupção. É um bom momento para canalizar essa intensidade em arte e cura. Considere que sua intuição é um guia seguro para transformar qualquer instabilidade em um renascimento suave e cheio de esperança.","palavra_do_dia":"Renovação","frase_do_dia":"Sua luz interior transforma os desafios em novas formas de florescer.","simbolo_emoji":"🌊","simbolo_nome":"Onda","cor_nome":"Azul Profundo","numero_simbolico":42,"significado_numero":"Representa a harmonia entre o mundo material e a sua intuição.","conselho":"Respire fundo e deixe que suas emoções fluam com serenidade e leveza.","numeros_sorte":[18,27,43,50,51,53],"indicadores_dia":{"amor":78,"saudade":80,"trabalho":58,"financas":41,"dinheiro":69,"sorte":61,"humor":58,"energia":80,"saude":48,"amizade":90,"estudos":38,"criatividade":43}}