{"signo":"Libra","data":"2026-07-20","idioma":"en-US","fato_historico":"1871: British Columbia joins the Canadian Confederation.","titulo":"Harmonious Unions and New Horizons","energia_do_dia":"Today brings a lovely celestial breeze, encouraging you to bridge gaps and build lasting partnerships. Much like the historic moment when diverse lands united to form a greater whole, you may find that collaborating with others strengthens your own foundation. It is a wonderful time to negotiate, compromise, and welcome fresh alliances into your world.","palavra_do_dia":"Unity","frase_do_dia":"Together we weave a tapestry far more beautiful than any singular thread.","simbolo_emoji":"🍀","simbolo_nome":"Four-leaf clover","cor_nome":"Sage Green","cor_hexadecimal":"#9DC183","numero_simbolico":18,"significado_numero":"Represents the manifestation of abundance through cooperative and diplomatic efforts.","conselho":"Consider hosting a gathering or reaching out to a friend for meaningful collaboration.","numeros_sorte":[4,11,31,35,48,58],"indicadores_dia":{"amor":63,"saudade":57,"trabalho":69,"financas":100,"dinheiro":41,"sorte":82,"humor":76,"energia":95,"saude":54,"amizade":10,"estudos":79,"criatividade":98}}