{"signo":"Capricornio","data":"2026-07-24","idioma":"en-US","fato_historico":"2024: A Saurya Airlines Bombardier CRJ200 crashes during takeoff from Tribhuvan International Airport in Kathmandu, Nepal killing 18.","titulo":"Embrace Your Inner Mountain Climber","energia_do_dia":"Today, you may feel an extra layer of resilience as you navigate your professional path. Much like the steady wings that rise above the clouds, consider how you can soar past obstacles with grace. It is a good time to reflect on the fragility of life and prioritize the connections that truly ground your ambitious spirit.","palavra_do_dia":"Resilience","frase_do_dia":"Even the highest peaks are reached one careful step at a time.","simbolo_emoji":"🍀","simbolo_nome":"Four-leaf Clover","cor_nome":"Earth Sage","cor_hexadecimal":"#8A9A5B","numero_simbolico":18,"significado_numero":"Represents the path of inner intuition and navigating through unseen challenges.","conselho":"Value your journey today and offer extra kindness to those around you.","numeros_sorte":[7,21,29,42,49,51],"indicadores_dia":{"amor":48,"amizade":53,"familia":59,"trabalho":67,"dinheiro":57,"sorte":72,"humor":88,"energia":58,"saude":82,"estudos":66,"criatividade":92,"intuicao":32}}