{"signo":"Gemeos","data":"2026-07-24","idioma":"pt-BR","fato_historico":"1567: Maria, Rainha da Escócia, é forçada a abdicar, e é sucedida pelo filho ainda criança, Jaime VI.","titulo":"Renovação e novas lideranças internas","energia_do_dia":"Hoje é um bom momento para considerar as mudanças de ciclos em sua vida, lembrando que soltar pesos antigos, tal como uma rainha que passa a coroa ao sucessor, pode abrir espaço para novas potências. Sua mente versátil de Gêmeos está pronta para abraçar novas formas de exercer o comando sobre suas próprias escolhas e emoções com sabedoria.","palavra_do_dia":"Transformação","frase_do_dia":"Deixar ir o que foi nos permite abraçar o que está por vir.","simbolo_emoji":"👑","simbolo_nome":"Coroa","cor_nome":"Amarelo Ouro","cor_hexadecimal":"#FFD700","numero_simbolico":24,"significado_numero":"Representa o equilíbrio entre o cuidado com o outro e a autogestão.","conselho":"Delegue tarefas e permita que novos começos floresçam em sua rotina hoje.","numeros_sorte":[22,23,24,29,34,40],"indicadores_dia":{"amor":88,"amizade":67,"familia":69,"trabalho":85,"dinheiro":41,"sorte":96,"humor":38,"energia":47,"saude":29,"estudos":11,"criatividade":23,"intuicao":22}}