{"signo":"Peixes","data":"2026-07-19","idioma":"pt-BR","fato_historico":"1544: Guerra italiana de 1542–46: começa o primeiro Cerco de Bolonha do Mar.","titulo":"Sua sensibilidade é sua força","energia_do_dia":"Hoje a energia convida a olhar para as muralhas internas que você talvez tenha erguido. Assim como as antigas defesas de Bolonha que um dia enfrentaram desafios, você pode sentir vontade de se proteger, mas o momento pede abertura. Respire fundo, deixe as águas fluírem e permita que novas conexões curem velhas feridas com gentileza e esperança renovada.","palavra_do_dia":"Fluidez","frase_do_dia":"Deixe que o rio da vida leve o que não lhe serve mais.","simbolo_emoji":"🐚","simbolo_nome":"Concha do Mar","cor_nome":"Azul Profundo","cor_hexadecimal":"#0047AB","numero_simbolico":19,"significado_numero":"Representa o fim de um ciclo e o início de novos horizontes.","conselho":"Considere perdoar a si mesmo e soltar o peso do passado hoje.","numeros_sorte":[8,22,23,41,45,54],"indicadores_dia":{"amor":59,"saudade":76,"trabalho":17,"financas":81,"dinheiro":12,"sorte":56,"humor":32,"energia":12,"saude":80,"amizade":82,"estudos":12,"criatividade":12}}