{"signo":"Peixes","data":"2026-07-22","idioma":"es-ES","fato_historico":"1962: Estados Unidos lanza la sonda estadounidense Mariner 1 hacia Venus, pero tras varios minutos de vuelo errático debe destruirse.","titulo":"Fluye con la marea estelar","energia_do_dia":"La energía de hoy te invita a soltar viejas trayectorias que no dieron el resultado esperado. Como aquella sonda que buscaba el horizonte venusiano, a veces los caminos se desvían, pero el aprendizaje permanece. Es un buen momento para navegar hacia nuevas metas con esperanza, permitiendo que tu intuición sea tu brújula más certera bajo este cielo protector.","palavra_do_dia":"Resiliencia","frase_do_dia":"Cada desvío en el mapa es una oportunidad para descubrir un nuevo destino.","simbolo_emoji":"🌊","simbolo_nome":"Onda","cor_nome":"Azul Profundo","cor_hexadecimal":"#003366","numero_simbolico":7,"significado_numero":"Representa la búsqueda espiritual y la sabiduría interior que guía tus pasos.","conselho":"Confía en tus corazonadas y no temas corregir el rumbo si es necesario.","numeros_sorte":[5,17,19,35,40,47],"indicadores_dia":{"amor":26,"amizade":51,"familia":16,"trabalho":43,"dinheiro":47,"sorte":61,"humor":95,"energia":54,"saude":86,"estudos":88,"criatividade":63,"intuicao":72}}