{"signo":"Sagitario","data":"2026-07-22","idioma":"es-ES","fato_historico":"1971: en Sudán, el jefe del Estado y primer ministro Yaafar al-Numeiry reasume el poder solo tres días después de ser derrocado por un golpe militar.","titulo":"el renacer de tu fuego","energia_do_dia":"Hoy la energía te invita a reflexionar sobre la resiliencia. Tal vez sientas una fuerza renovada, similar a quien recupera su trono interior tras una tormenta inesperada. Es un buen momento para retomar proyectos pausados y confiar en que, tras cualquier desorden, siempre surge una nueva oportunidad para liderar tu propio destino con sabiduría y mucha esperanza.","palavra_do_dia":"Resiliencia","frase_do_dia":"Tu espíritu es invencible y siempre encuentra el camino de vuelta a casa.","simbolo_emoji":"🔥","simbolo_nome":"Fuego eterno","cor_nome":"Terracota","cor_hexadecimal":"#E2725B","numero_simbolico":7,"significado_numero":"Representa la búsqueda de la verdad y el crecimiento espiritual profundo.","conselho":"Considera retomar hoy ese plan que dejaste a medias; la suerte te acompaña.","numeros_sorte":[6,38,43,47,58,60],"indicadores_dia":{"amor":48,"amizade":44,"familia":59,"trabalho":37,"dinheiro":50,"sorte":32,"humor":95,"energia":23,"saude":25,"estudos":98,"criatividade":57,"intuicao":31}}