{"signo":"Aries","data":"2026-07-18","idioma":"es-ES","fato_historico":"1290: en Inglaterra, el rey Eduardo I expulsa a los judíos (unos 16 000) mediante un Edicto de expulsión.","titulo":"Renueva tu fuerza interior Aries","energia_do_dia":"Hoy la energía te invita a reflexionar sobre los límites y las fronteras que construimos. Al igual que en tiempos antiguos, donde las decisiones reales cambiaron el mapa de una nación, tú puedes hoy decidir qué personas o ideas merecen un lugar en tu corazón. Es un buen momento para abrir nuevas puertas y dejar atrás lo que ya no encaja.","palavra_do_dia":"Renovación","frase_do_dia":"Tu valentía es el puente hacia una nueva y maravillosa etapa personal.","simbolo_emoji":"🔑","simbolo_nome":"Llave","cor_nome":"Carmesí","cor_hexadecimal":"#DC143C","numero_simbolico":7,"significado_numero":"Siete es el número de la introspección y la sabiduría espiritual profunda.","conselho":"Considera perdonar una herida del pasado para liberar espacio a la fortuna.","numeros_sorte":[23,28,37,41,42,50],"indicadores_dia":{"amor":48,"saudade":25,"trabalho":62,"financas":70,"dinheiro":72,"sorte":34,"humor":74,"energia":82,"saude":91,"amizade":62,"estudos":46,"criatividade":36}}